{"app":"Pothole Radar Mumbai","insights_version":"direct-bmc-2026-07-03.1","generated_at":"2026-07-09T07:45:13Z","data":{"total_potholes":2453,"active_potholes":327,"resolved_potholes":2126,"invalid_potholes":1212,"reopened_potholes":11,"pending_potholes":327,"resolution_rate_percent":86.7,"active_rate_percent":13.3,"average_resolution_hours":86.6,"median_resolution_hours":24.2,"latest_complaint_date":"2026-07-09T07:42:59Z","latest_resolved_date":"2026-07-09T07:40:59Z","data_last_updated":"2026-07-09T07:45:13Z","top_affected_ward":"Unknown","top_affected_locality":"Nehru Nagar — L Ward","top_affected_zone":"V","top_affected_road_type":"Unknown"}}