{"app":"Pothole Radar Mumbai","insights_version":"2026-07-01.1","generated_at":"2026-07-03T17:10:05Z","data":{"total_potholes":1419,"active_potholes":160,"resolved_potholes":1259,"invalid_potholes":907,"reopened_potholes":2,"pending_potholes":160,"resolution_rate_percent":88.7,"active_rate_percent":11.3,"average_resolution_hours":113.3,"median_resolution_hours":29.1,"latest_complaint_date":"2026-07-02T11:11:35Z","latest_resolved_date":"2026-07-02T11:02:48Z","data_last_updated":"2026-07-03T17:10:05Z","top_affected_ward":"GN","top_affected_locality":"Dharavi — G/N Ward","top_affected_zone":"IV","top_affected_road_type":"Unknown"}}