{"app":"Pothole Radar Mumbai","insights_version":"direct-bmc-2026-07-03.1","generated_at":"2026-07-07T13:00:15Z","data":[{"road_type":"Major Road","total_count":618,"active_count":196,"resolved_count":422,"invalid_count":3,"reopened_count":7,"pending_count":196,"resolution_rate_percent":68.3,"active_rate_percent":31.7,"average_resolution_hours":111.4,"median_resolution_hours":65.9,"latest_complaint_date":"2026-07-07T11:53:51Z","latest_resolved_date":"2026-07-07T12:55:40Z"},{"road_type":"Unknown","total_count":1380,"active_count":60,"resolved_count":1320,"invalid_count":1130,"reopened_count":2,"pending_count":60,"resolution_rate_percent":95.7,"active_rate_percent":4.3,"average_resolution_hours":87.5,"median_resolution_hours":15.6,"latest_complaint_date":"2026-07-07T12:41:14Z","latest_resolved_date":"2026-07-07T12:37:37Z"},{"road_type":"Minor Road","total_count":99,"active_count":21,"resolved_count":78,"invalid_count":1,"reopened_count":1,"pending_count":21,"resolution_rate_percent":78.8,"active_rate_percent":21.2,"average_resolution_hours":111.7,"median_resolution_hours":50.8,"latest_complaint_date":"2026-07-07T09:37:15Z","latest_resolved_date":"2026-07-07T09:47:16Z"}]}