{"app":"Pothole Radar Mumbai","insights_version":"2026-07-01.1","generated_at":"2026-07-02T09:30:44Z","data":[{"road_type":"Unknown","total_count":1060,"active_count":70,"resolved_count":990,"invalid_count":898,"reopened_count":0,"pending_count":70,"resolution_rate_percent":93.4,"active_rate_percent":6.6,"average_resolution_hours":107.4,"median_resolution_hours":20.6,"latest_complaint_date":"2026-07-02T09:18:54Z","latest_resolved_date":"2026-07-02T08:01:21Z"},{"road_type":"Major Road","total_count":281,"active_count":70,"resolved_count":211,"invalid_count":3,"reopened_count":1,"pending_count":70,"resolution_rate_percent":75.1,"active_rate_percent":24.9,"average_resolution_hours":148.0,"median_resolution_hours":82.0,"latest_complaint_date":"2026-07-02T06:29:32Z","latest_resolved_date":"2026-07-02T09:07:39Z"},{"road_type":"Minor Road","total_count":60,"active_count":12,"resolved_count":48,"invalid_count":1,"reopened_count":1,"pending_count":12,"resolution_rate_percent":80.0,"active_rate_percent":20.0,"average_resolution_hours":148.2,"median_resolution_hours":66.4,"latest_complaint_date":"2026-07-01T17:29:20Z","latest_resolved_date":"2026-07-02T08:39:33Z"}]}