{"app":"Pothole Radar Mumbai","insights_version":"direct-bmc-2026-07-03.1","generated_at":"2026-07-09T08:15:16Z","data":[{"road_type":"Major Road","total_count":819,"active_count":218,"resolved_count":601,"invalid_count":3,"reopened_count":9,"pending_count":218,"resolution_rate_percent":73.4,"active_rate_percent":26.6,"average_resolution_hours":98.1,"median_resolution_hours":60.3,"latest_complaint_date":"2026-07-09T06:34:21Z","latest_resolved_date":"2026-07-09T08:12:31Z"},{"road_type":"Unknown","total_count":1515,"active_count":73,"resolved_count":1442,"invalid_count":1211,"reopened_count":2,"pending_count":73,"resolution_rate_percent":95.2,"active_rate_percent":4.8,"average_resolution_hours":81.3,"median_resolution_hours":14.6,"latest_complaint_date":"2026-07-09T08:15:19Z","latest_resolved_date":"2026-07-09T08:12:05Z"},{"road_type":"Minor Road","total_count":127,"active_count":34,"resolved_count":93,"invalid_count":1,"reopened_count":0,"pending_count":34,"resolution_rate_percent":73.2,"active_rate_percent":26.8,"average_resolution_hours":106.8,"median_resolution_hours":52.2,"latest_complaint_date":"2026-07-09T05:26:30Z","latest_resolved_date":"2026-07-09T08:03:46Z"}]}