{"app":"Pothole Radar Mumbai","insights_version":"direct-bmc-2026-07-03.1","generated_at":"2026-07-06T05:30:16Z","data":[{"zone":"V","total_count":313,"active_count":62,"resolved_count":251,"invalid_count":163,"reopened_count":2,"pending_count":62,"resolution_rate_percent":80.2,"active_rate_percent":19.8,"average_resolution_hours":97.3,"median_resolution_hours":22.8,"latest_complaint_date":"2026-07-05T18:10:16Z","latest_resolved_date":"2026-07-06T03:44:57Z"},{"zone":"VI","total_count":206,"active_count":51,"resolved_count":155,"invalid_count":106,"reopened_count":1,"pending_count":51,"resolution_rate_percent":75.2,"active_rate_percent":24.8,"average_resolution_hours":55.7,"median_resolution_hours":12.6,"latest_complaint_date":"2026-07-06T04:14:52Z","latest_resolved_date":"2026-07-06T03:52:05Z"},{"zone":"II","total_count":284,"active_count":49,"resolved_count":235,"invalid_count":150,"reopened_count":3,"pending_count":49,"resolution_rate_percent":82.7,"active_rate_percent":17.3,"average_resolution_hours":107.7,"median_resolution_hours":43.2,"latest_complaint_date":"2026-07-06T05:27:40Z","latest_resolved_date":"2026-07-06T05:25:40Z"},{"zone":"IV","total_count":320,"active_count":47,"resolved_count":273,"invalid_count":159,"reopened_count":1,"pending_count":47,"resolution_rate_percent":85.3,"active_rate_percent":14.7,"average_resolution_hours":106.2,"median_resolution_hours":19.3,"latest_complaint_date":"2026-07-06T03:33:36Z","latest_resolved_date":"2026-07-06T05:30:15Z"},{"zone":"I","total_count":268,"active_count":39,"resolved_count":229,"invalid_count":169,"reopened_count":0,"pending_count":39,"resolution_rate_percent":85.4,"active_rate_percent":14.6,"average_resolution_hours":94.5,"median_resolution_hours":41.8,"latest_complaint_date":"2026-07-06T04:58:42Z","latest_resolved_date":"2026-07-06T05:30:06Z"},{"zone":"VII","total_count":244,"active_count":30,"resolved_count":214,"invalid_count":156,"reopened_count":0,"pending_count":30,"resolution_rate_percent":87.7,"active_rate_percent":12.3,"average_resolution_hours":90.1,"median_resolution_hours":20.9,"latest_complaint_date":"2026-07-05T17:33:45Z","latest_resolved_date":"2026-07-05T18:48:19Z"},{"zone":"III","total_count":263,"active_count":25,"resolved_count":238,"invalid_count":159,"reopened_count":1,"pending_count":25,"resolution_rate_percent":90.5,"active_rate_percent":9.5,"average_resolution_hours":107.5,"median_resolution_hours":34.1,"latest_complaint_date":"2026-07-06T02:26:15Z","latest_resolved_date":"2026-07-05T22:10:32Z"},{"zone":"Unknown","total_count":3,"active_count":0,"resolved_count":3,"invalid_count":2,"reopened_count":0,"pending_count":0,"resolution_rate_percent":100.0,"active_rate_percent":0.0,"average_resolution_hours":442.9,"median_resolution_hours":577.4,"latest_complaint_date":"2026-06-26T01:00:31Z","latest_resolved_date":"2026-07-02T13:40:44Z"}]}