{"cell":"te7u99","manifest_version":"2026-07-03T01:23:36Z","generated_at":"2026-07-03T01:23:36Z","count":1,"potholes":[{"objectid":15377,"complaints_id":"HE_202600056014","status":"In Review","substatus":null,"ward_name":"HE","zone":"III","division":"Western","road_type":null,"description":"After just two days of rain, this is the condition of the roads in Vakola, Anand Nagar, near Ganesh Mandir, Santacruz East This is unacceptable and poses a serious inconvenience and safety risk to residents and commuters @mybmcWardHE pls take immedi","landmark":null,"latitude":19.0817,"longitude":72.84773,"image_urls":["https://marg.mcgm.gov.in/image-upload-api/images/MyBMC%20MARG/HE_202600056014/Initial%20Image%20By%20Citizen.jpeg"],"complaints_creation_date":"2026-07-02T07:50:00Z","resolved_date":null,"updated_at":"2026-07-02T11:22:47Z","location_name":"Vakola","ward_code":"H/E","display_location":"Vakola — H/E Ward"}]}