{"cell":"te7uf7","manifest_version":"2026-07-07T08:15:15Z","generated_at":"2026-07-07T08:15:15Z","count":1,"potholes":[{"objectid":3558,"complaints_id":"KN_202600036809","complaint_type":"Pothole","status":"Resolved","substatus":null,"ward_name":"KN","ward_code":null,"zone":"III","division":"Western","road_type":null,"description":"खड्ड्यामुळे स्थानिक वर्ग प्रवासी वर्ग खूप त्रासलेली आहेत खड्ड्यामुळे कोणताही अपघात होण्याची शक्यता आहे","landmark":"gautam nagar kachha rastta","complaint_source":"MyBMC MARG","latitude":19.13793,"longitude":72.8727767,"valid_image":null,"confirm_image":null,"confirm_postwork_image":null,"images":"Initial Image By Citizen.jpg","image_urls":["https://marg.mcgm.gov.in/image-upload-api/images/MyBMC%20MARG/KN_202600036809/Initial%20Image%20By%20Citizen.jpg"],"complaints_creation_date":"2026-06-05T17:02:36Z","resolved_date":"2026-06-20T05:32:15Z","updated_at":"2026-07-07T08:15:15Z","location_name":"Jogeshwari East","display_location":"Jogeshwari East, Mumbai"}]}