{"cell":"te7ug3","manifest_version":"2026-07-05T01:30:19Z","generated_at":"2026-07-05T01:30:19Z","count":2,"potholes":[{"objectid":13215,"complaints_id":"SX_202600053238","complaint_type":"Pothole","status":"Resolved","substatus":"Invalid","ward_name":"S","ward_code":"S","zone":"VI","division":"Eastern","road_type":null,"description":null,"landmark":"near petrol punp","complaint_source":"MyBMC MARG","latitude":19.1248453,"longitude":72.9250571,"valid_image":"No","confirm_image":null,"confirm_postwork_image":null,"images":"Initial Image By Citizen.jpg","image_urls":["https://marg.mcgm.gov.in/image-upload-api/images/MyBMC%20MARG/SX_202600053238/Initial%20Image%20By%20Citizen.jpg","https://marg.mcgm.gov.in/image-upload-api/images/MyBMC%20MARG/SX_202600053238/No"],"complaints_creation_date":"2026-06-27T17:10:34Z","resolved_date":"2026-06-28T07:47:01Z","updated_at":"2026-07-05T01:30:19Z","location_name":"Kannamwar Nagar","display_location":"Kannamwar Nagar — S Ward"},{"objectid":13271,"complaints_id":"SX_202600052347","complaint_type":"Pothole","status":"Resolved","substatus":"Invalid","ward_name":"S","ward_code":"S","zone":"VI","division":"Eastern","road_type":null,"description":null,"landmark":"in front of sun heights apartment near suncity complex","complaint_source":"MyBMC MARG","latitude":19.1246868,"longitude":72.9213534,"valid_image":"No","confirm_image":null,"confirm_postwork_image":null,"images":"Initial Image By Citizen.jpg","image_urls":["https://marg.mcgm.gov.in/image-upload-api/images/MyBMC%20MARG/SX_202600052347/Initial%20Image%20By%20Citizen.jpg","https://marg.mcgm.gov.in/image-upload-api/images/MyBMC%20MARG/SX_202600052347/No"],"complaints_creation_date":"2026-06-26T11:59:36Z","resolved_date":"2026-06-26T12:51:43Z","updated_at":"2026-07-05T01:30:19Z","location_name":"Hiranandani Powai","display_location":"Hiranandani Powai — S Ward"}]}