{"cell":"te7u19","manifest_version":"2026-07-04T04:09:14Z","generated_at":"2026-07-04T04:09:14Z","count":1,"potholes":[{"objectid":13775,"complaints_id":"FS_202600054214","status":"In Review","substatus":null,"ward_name":"FS","zone":"II","division":"City","road_type":null,"description":null,"landmark":"Lane near Kamal Darshan, Lalbaug","latitude":18.9910123,"longitude":72.8393836,"image_urls":["https://marg.mcgm.gov.in/image-upload-api/images/MyBMC%20MARG/FS_202600054214/Initial%20Image%20By%20Citizen.jpg"],"complaints_creation_date":"2026-06-29T11:10:30Z","resolved_date":null,"updated_at":"2026-07-02T11:22:47Z","location_name":"Kalachowki","ward_code":"F/S","display_location":"Kalachowki — F/S Ward"}]}