{"cell":"te7v1f","manifest_version":"2026-07-02T06:04:13Z","generated_at":"2026-07-02T06:04:13Z","count":2,"potholes":[{"objectid":12169,"complaints_id":"PE_202600050401","status":"In Progress","substatus":null,"ward_name":"PE","zone":"IV","division":"Western","road_type":null,"description":"please fix this pothole","landmark":"15 feets away from dindoshi metro station","latitude":19.17662058,"longitude":72.85868454,"image_urls":["https://marg.mcgm.gov.in/image-upload-api/images/MyBMC%20MARG/PE_202600050401/Initial%20Image%20By%20Citizen.jpg"],"complaints_creation_date":"2026-06-24T10:07:58Z","resolved_date":null,"updated_at":"2026-07-02T06:04:12Z","location_name":"Dindoshi","ward_code":null,"display_location":"Dindoshi, Mumbai"},{"objectid":1649,"complaints_id":"PS_202600032914","status":"In Progress","substatus":null,"ward_name":"PS","zone":"IV","division":"Western","road_type":null,"description":null,"landmark":"please see GPS photo","latitude":19.17447972,"longitude":72.85924583,"image_urls":["https://marg.mcgm.gov.in/image-upload-api/images/MyBMC%20MARG/PS_202600032914/Initial%20Image%20By%20Citizen.jpg"],"complaints_creation_date":"2026-05-31T18:31:50Z","resolved_date":null,"updated_at":"2026-07-02T06:04:12Z","location_name":"Dindoshi","ward_code":"P/S","display_location":"Dindoshi — P/S Ward"}]}